swiftstorage/__init__.py
swiftstorage/swiftstorage.py
swiftstorage/classes/__init__.py
swiftstorage/classes/local.py
swiftstorage/classes/remote.py
swiftstorage/core/specification.py
swiftstorage/core/stream.py
swiftstorage/examples/encrypt.py
swiftstorage/examples/propagate.py
swiftstorage/examples/transfer.py
swiftstorage/utilities/helpers.py
swiftstorage/utilities/logging.py
swiftstorage-0.4.0.dist-info/METADATA
swiftstorage-0.4.0.dist-info/WHEEL
swiftstorage-0.4.0.dist-info/licenses/LICENSE
swiftstorage-0.4.0.dist-info/RECORD
