Metadata-Version: 2.4
Name: swiftstorage
Version: 0.4.0
Summary: A simple way to interact with local and remote file systems. Easily extendable to support custom endpoints.
Project-URL: Homepage, https://github.com/SeanYeatts/SwiftStorage
Author: Sean Yeatts
License: MIT License
License-File: LICENSE
Classifier: License :: OSI Approved :: MIT License
Classifier: Operating System :: Microsoft :: Windows
Classifier: Programming Language :: Python :: 3
Requires-Python: >=3.13
